assistant_improve_toolkit/__init__.py
assistant_improve_toolkit/computation_func.py
assistant_improve_toolkit/cos_op.py
assistant_improve_toolkit/export_csv_for_intent_recommendation.py
assistant_improve_toolkit/fetch_logs.py
assistant_improve_toolkit/version.py
assistant_improve_toolkit/visualize_func.py
assistant_improve_toolkit/watson_assistant_func.py
main/__init__.py
main/python/__init__.py
main/python/computation_func.py
main/python/cos_op.py
main/python/export_csv_for_intent_recommendation.py
main/python/fetch_logs.py
main/python/visualize_func.py
main/python/watson_assistant_func.py
main/python/watson_assistant_func_skip.py
assistant_improve_toolkit-1.4.1.dist-info/LICENSE
assistant_improve_toolkit-1.4.1.dist-info/METADATA
assistant_improve_toolkit-1.4.1.dist-info/WHEEL
assistant_improve_toolkit-1.4.1.dist-info/top_level.txt
assistant_improve_toolkit-1.4.1.dist-info/RECORD
