Metadata-Version: 2.1
Name: assistant-improve-toolkit
Version: 1.4.1
Summary: Assistant Improve Toolkit
Home-page: https://github.com/watson-developer-cloud/assistant-improve-recommendations-notebook
Author: IBM Watson
Author-email: watdevex@us.ibm.com
Maintainer: Zhe Zhang
Maintainer-email: zhangzhe@us.ibm.com
License: Apache 2.0
Platform: any
Classifier: Development Status :: 4 - Beta
Classifier: Intended Audience :: Developers
Classifier: License :: OSI Approved :: Apache Software License
Classifier: Programming Language :: Python
Classifier: Programming Language :: Python :: 3.7
Classifier: Programming Language :: Python :: 3.8
Classifier: Operating System :: OS Independent
Classifier: Topic :: Software Development :: Libraries :: Python Modules
License-File: LICENSE
Requires-Dist: pandas (==1.2.1)
Requires-Dist: bokeh (==3.2.0)
Requires-Dist: tqdm (==4.65.0)
Requires-Dist: scikit-learn (>=0.21.3)
Requires-Dist: matplotlib (==3.2.1)
Requires-Dist: XlsxWriter (==1.2.8)
Requires-Dist: ibm-watson (==7.0.0)
Requires-Dist: numpy (==1.23.5)
Requires-Dist: requests (==2.29.0)
